<?xml version="1.0" encoding="UTF-8"?>
<!DOCTYPE schedule SYSTEM "timetable.dtd">
<schedule>
	<year>2016</year>
	<term>Winter</term>
	<set>4O</set>
		<!-- begin days of week table -->
	<daysofweek>
		<day name = "monday">
			<dbooking>
				<room>SE12-323</room>
				<time start = "9:30" end = "11:20"></time>
				<course num = "COMP4985"/>
				<instructor>Aman Abdulla</instructor>
				<type>Lab</type>
			</dbooking>
			<dbooking>
				<room>SW1-1205</room>
				<time start = "11:30" end = "12:20"></time>
				<course num = "COMP4735"/>
				<instructor>Mirela Gutica</instructor>
				<type>Lecture</type>
			</dbooking>
			<dbooking>
				<room>SW9-127</room>
				<time start = "12:30" end = "14:20"></time>
				<course num = "BLAW 360"/>
				<instructor>Catherine Ryan</instructor>
				<type>Lab</type>
			</dbooking>
			<dbooking>
				<room>SE12-320</room>
				<time start = "15:30" end = "17:20"></time>
				<course num = "COMP4560"/>
				<instructor>Brenda Fine</instructor>
				<type>Lab</type>
			</dbooking>
		</day>
		<day name = "tuesday">
			<dbooking>
				<room>SE12-323</room>
				<time start = "9:30" end = "11:20"></time>
				<course num = "COMP4981"/>
				<instructor>Aman Abdulla</instructor>
				<type>Lab</type>
			</dbooking>
			<dbooking>
				<room>SW5-1850</room>
				<time start = "11:30" end = "12:20"></time>
				<course num = "COMP4560"/>
				<instructor>Brenda Fine</instructor>
				<type>Lecture</type>
			</dbooking>
			<dbooking>
				<room>SW5-1850</room>
				<time start = "14:30" end = "15:20"></time>
				<course num = "COMP4711"/>
				<instructor>James Parry</instructor>
				<type>Lecture</type>
			</dbooking>
			<dbooking>
				<room>SE32-321</room>
				<time start = "15:30" end = "17:20"></time>
				<course num = "COMP4711"/>
				<instructor>James Parry</instructor>
				<type>Lab</type>
			</dbooking>
		</day>
		<day name = "wednesday">
			<dbooking>
				<room>SE12-323</room>
				<time start = "9:30" end = "11:20"></time>
				<course num = "COMP4985"/>
				<instructor>Aman Abdulla</instructor>
				<type>Lecture</type>
			</dbooking>
			<dbooking>
				<room>SE12-323</room>
				<time start = "11:30" end = "12:20"></time>
				<course num = "COMP4985"/>
				<instructor>Aman Abdulla</instructor>
				<type>Lecture</type>
			</dbooking>
			<dbooking>
				<room>SE12-323</room>
				<time start = "12:30" end = "13:20"></time>
				<course num = "COMP4981"/>
				<instructor>Aman Abdulla</instructor>
				<type>Lecture</type>
			</dbooking>
			<dbooking>
				<room>SW1-1205</room>
				<time start = "13:30" end = "14:20"></time>
				<course num = "COMP4735"/>
				<instructor>Mirela Gutica</instructor>
				<type>Lecture</type>
			</dbooking>
		</day>
		<day name = "thursday">
			<dbooking>
				<room>SE12-323</room>
				<time start = "9:30" end = "11:20"></time>
				<course num = "COMP4981"/>
				<instructor>Aman Abdulla</instructor>
				<type>Lecture</type>
			</dbooking>
			<dbooking>
				<room>SW3-1710</room>
				<time start = "11:30" end = "12:20"></time>
				<course num = "COMP4735"/>
				<instructor>Mirela Gutica</instructor>
				<type>Lecture</type>
			</dbooking>
			<dbooking>
				<room>SE12-322</room>
				<time start = "15:30" end = "17:20"></time>
				<course num = "COMP4981"/>
				<instructor>Linder Mathew</instructor>
				<type>Lab</type>
			</dbooking>
		</day>
		<day name = "friday">
			<dbooking>
				<room>SW5-1840</room>
				<time start = "8:30" end = "10:20"></time>
				<course num = "BLAW3600"/>
				<instructor>Kevin Wainwright</instructor>
				<type>Lecture</type>
			</dbooking>
			<dbooking>
				<room>SW3-1710</room>
				<time start = "12:30" end = "13:20"></time>
				<course num = "COMP4560"/>
				<instructor>Breanda Fine</instructor>
				<type>Lecture</type>
			</dbooking>
		</day>
	</daysofweek>
	<!-- end days of week table -->
    <timeslots>
		<slots start = "9:30" end = "11:20">
			<time start = "9:30" end = "11:20"/>
			<tbooking>
				<room>SE12-323</room>
				<day name="monday"/>
				<course num = "COMP4985"/>
				<instructor>Aman Abdulla</instructor>
				<type>Lab</type>
			</tbooking>
		</slots>
		<slots start = "11:30" end = "12:20">
			<time start = "11:30" end = "12:20"/>
			<tbooking>
				<room>SW1-1205</room>
				<day name="monday"/>
				<course num = "COMP4735"/>
				<instructor>Mirela Guticaa</instructor>
				<type>Lecture</type>
			</tbooking>
		</slots>
		<slots start = "12:30" end = "13:20">
			<time start = "12:30" end = "13:20"/>
			<tbooking>
				<room>SE12-307</room>
				<day name="monday"/>
				<course num = "BLAW3600"/>
				<instructor>Catherine Ryan</instructor>
				<type>Lab</type>
			</tbooking>
		</slots>
		<slots start = "15:30" end = "17:20">
			<time start = "15:30" end = "17:20"/>
			<tbooking>
				<room>SE12-320</room>
				<day name="monday"/>
				<course num = "COMP4560"/>
				<instructor>Brenda Fine</instructor>
				<type>Lab</type>
			</tbooking>
		</slots>
		<slots start = "9:30" end = "11:20">
			<time start = "9:30" end = "11:20"/>
			<tbooking>
				<room>SE12-323</room>
				<day name="tuesday"/>
				<course num = "COMP4981"/>
				<instructor>Aman Abdulla</instructor>
				<type>Lab</type>
			</tbooking>
		</slots>
		<slots start = "11:30" end = "12:20">
			<time start = "11:30" end = "12:20"/>
			<tbooking>
				<room>SW5-323</room>
				<day name="tuesday"/>
				<course num = "COMP4560"/>
				<instructor>Brenda Fine</instructor>
				<type>Lecture</type>
			</tbooking>
		</slots>
		<slots start = "14:30" end = "15:20">
			<time start = "14:30" end = "15:20"/>
			<tbooking>
				<room>SW5-1840</room>
				<day name="tuesday"/>
				<course num = "COMP4711"/>
				<instructor>James Parry</instructor>
				<type>Lecture</type>
			</tbooking>
		</slots>
		<slots start = "15:30" end = "17:20">
			<time start = "15:30" end = "17:20"/>
			<tbooking>
				<room>SE12-321</room>
				<day name="tuesday"/>
				<course num = "COMP4711"/>
				<instructor>James Parry</instructor>
				<type>Lab</type>
			</tbooking>
		</slots>
		<slots start = "9:30" end = "11:20">
			<time start = "9:30" end = "11:20"/>
			<tbooking>
				<room>SE12-323</room>
				<day name="wednesday"/>
				<course num = "COMP4985"/>
				<instructor>Aman Abdulla</instructor>
				<type>Lecture</type>
			</tbooking>
		</slots>
		<slots start = "11:30" end = "12:20">
			<time start = "11:30" end = "12:20"/>
			<tbooking>
				<room>SE12-323</room>
				<day name="wednesday"/>
				<course num = "COMP4985"/>
				<instructor>Aman Abdulla</instructor>
				<type>Lecture</type>
			</tbooking>
		</slots>
		<slots start = "12:30" end = "13:20">
			<time start = "12:30" end = "13:20"/>
			<tbooking>
				<room>SE12-323</room>
				<day name="wednesday"/>
				<course num = "COMP4981"/>
				<instructor>Aman Abdulla</instructor>
				<type>Lecture</type>
			</tbooking>
		</slots>
		<slots start = "13:30" end = "14:20">
			<time start = "13:30" end = "14:20"/>
			<tbooking>
				<room>SW1-1205</room>
				<day name="wednesday"/>
				<course num = "COMP4735"/>
				<instructor>Mirela Guticaa</instructor>
				<type>Lecture</type>
			</tbooking>
		</slots>
		<slots start = "9:30" end = "11:20">
			<time start = "9:30" end = "11:20"/>
			<tbooking>
				<room>SE12-323</room>
				<day name="thursday"/>
				<course num = "COMP4981"/>
				<instructor>Aman Abdulla</instructor>
				<type>Lecture</type>
			</tbooking>
		</slots>
		<slots start = "11:30" end = "12:20">
			<time start = "11:30" end = "12:20"/>
			<tbooking>
				<room>SW3-1710</room>
				<day name="thursday"/>
				<course num = "COMP4735"/>
				<instructor>Mirela Guticaa</instructor>
				<type>Lecture</type>
			</tbooking>
		</slots>
		<slots start = "15:30" end = "17:20">
			<time start = "15:30" end = "17:20"/>
			<tbooking>
				<room>SE12-322</room>
				<day name="thursday"/>
				<course num = "COMP4735"/>
				<instructor>Matthew Linder</instructor>
				<type>Lab</type>
			</tbooking>
		</slots>
		<slots start = "8:30" end = "10:20">
			<time start = "8:30" end = "10:20"/>
			<tbooking>
				<room>SW5-1850</room>
				<day name="friday"/>
				<course num = "BLAW3600"/>
				<instructor>Catherine Ryan</instructor>
				<type>Lecture</type>
			</tbooking>
		</slots>
		<slots start = "12:30" end = "13:20">
			<time start = "12:30" end = "13:20"/>
			<tbooking>
				<room>SW1-1021</room>
				<day name="friday"/>
				<course num = "COMP4560"/>
				<instructor>Brenda Fine</instructor>
				<type>Lecture</type>
			</tbooking>
		</slots>
	</timeslots>
	<!-- begin courses table -->
	<courses>
		<course num="COMP4711">
			<cbooking>
				<day name="tuesday"/>
				<time start="13:30" end="14:20"/>
				<room>SW5-1840</room>
				<type>Lecture</type>
				<instructor>Jim Parry</instructor>
			</cbooking>
			<cbooking>
				<day name="tuesday"/>
				<time start="14:30" end="17:20"/>
				<room>SE12-321</room>
				<type>Lab</type>
				<instructor>Jim Parry</instructor>
			</cbooking> 
		</course> <!-- end COMP4711 -->
		<course num="COMP4985">
			<cbooking>
				<day name="monday"/>
				<time start="9:30" end="11:20"/>
				<room>SE12-323</room>
				<type>Lab</type>
				<instructor>Aman Abdulla</instructor> 
			</cbooking>
			<cbooking>
				<day name="wednesday"/>
				<time start="9:30" end="11:20"/>
				<room>SE12-323</room>
				<type>Lecture</type>
				<instructor>Aman Abdulla</instructor>
			</cbooking>
			<cbooking>
				<day name="wednesday"/>
				<time start="11:30" end="13:20"/>
				<room>SE12-323</room>
				<type>Lecture</type>
				<instructor>Aman Abdulla</instructor>
			</cbooking>
		</course> <!-- end COMP4985 -->
		<course num="COMP4981">
			<cbooking>
				<day name="tuesday"/>
				<time start="9:30" end="11:20"/>
				<room>SE12-323</room>
				<type>Lab</type>
				<instructor>Aman Abdulla</instructor>
			</cbooking>
			<cbooking>
				<day name="thursday"/>
				<time start="9:30" end="11:20"/>
				<room>SE12-323</room>
				<type>Lab</type>
				<instructor>Aman Abdulla</instructor>
			</cbooking>
		</course> <!-- end COMP4981 -->
		<course num="COMP4735">
			<cbooking>
				<day name="monday"/>
				<time start="11:30" end="12:20"/>
				<room>SW1-1205</room>
				<type>Lecture</type>
				<instructor>Mirela Gutica</instructor>
			</cbooking>
			<cbooking>
				<day name="wednesday"/>
				<time start="13:30" end="14:20"/>
				<room>SW1-1205</room>
				<type>Lecture</type>
				<instructor>Mirela Gutica</instructor>
			</cbooking>
			<cbooking>
				<day name="thursday"/>
				<time start="11:30" end="12:20"/>
				<room>SW1-1205</room>
				<type>Lecture</type>
				<instructor>Mirela Gutica</instructor>
			</cbooking>
		</course> <!-- end COMP4735 -->
		<course num="COMP4560">
			<cbooking>
				<day name="monday"/>
				<time start="15:30" end="17:20"/>
				<room>SE12-320</room>
				<type>Lab</type>
				<instructor>Brenda Fine</instructor>
			</cbooking>
			<cbooking>
				<day name="tuesday"/>
				<time start="11:30" end="12:20"/>
				<room>SW5-1850</room>
				<type>Lecture</type>
				<instructor>Brenda Fine</instructor>
			</cbooking>
			<cbooking>
				<day name="friday"/>
				<time start="12:30" end="13:20"/>
				<room>SW3-1750</room>
				<type>Lecture</type>
				<instructor>Brenda Fine</instructor>
			</cbooking>
		</course> <!-- end COMP4560 -->
		<course num="BLAW3600">
			<cbooking>
				<day name="monday"/>
				<time start="12:30" end="14:20"/>
				<room>SW9-127</room>
				<type>Lab</type>
				<instructor>Catherine Ryan</instructor>
			</cbooking>
			<cbooking>
				<day name="friday"/>
				<time start="8:30" end="10:20"/>
				<room>SW5-1840</room>
				<type>Lecture</type>
				<instructor>Kevin Wainwright</instructor>
			</cbooking>
		</course> <!-- end BLAW3600 -->
	</courses>
	<!-- end courses table -->
</schedule>
